auladio_criandopacotes/__init__.py
auladio_criandopacotes/functions/__init__.py
auladio_criandopacotes/functions/equalize.py
auladio_criandopacotes/functions/grayscale.py
auladio_criandopacotes/tools/__init__.py
auladio_criandopacotes/tools/io.py
auladio_criandopacotes/tools/plot.py
auladio_criandopacotes-0.0.0.1.dist-info/METADATA
auladio_criandopacotes-0.0.0.1.dist-info/WHEEL
auladio_criandopacotes-0.0.0.1.dist-info/top_level.txt
auladio_criandopacotes-0.0.0.1.dist-info/RECORD
