Metadata-Version: 2.4
Name: auladio_criandopacotes
Version: 0.0.0.1
Summary: pacote de processamento de imagens simples para aprender a mexer no Pypi
Author-email: Juliana Tiemi <tiemi.suyama@gmail.com>
Requires-Dist: scikit-image
Requires-Dist: matplotlib
Requires-Dist: numpy
Requires-Dist: importlib-metadata; python_version < "3.10"
